LICENSE
README.md
setup.py
keypad/__init__.py
keypad/i2ckeypad.py
keypad/keymaps/__init__.py
keypad/keymaps/matrix4x4.py
micropython_keypad.egg-info/PKG-INFO
micropython_keypad.egg-info/SOURCES.txt
micropython_keypad.egg-info/dependency_links.txt
micropython_keypad.egg-info/top_level.txt