Metadata-Version: 2.1
Name: micropython-keypad
Version: 0.6.0
Summary: Keypad library generic matrix keypads
Home-page: https://github.com/octopuslab-cz/micropython-keypad
Author: Petr Kracik
Author-email: petrkr@petrkr.net
License: MIT
Platform: UNKNOWN
Classifier: Programming Language :: Python :: 3
Classifier: License :: OSI Approved :: MIT License
Classifier: Operating System :: OS Independent
Classifier: Development Status :: 3 - Alpha
Requires-Python: >=3.4
License-File: LICENSE
